playerv5_tools_mcp/__init__.py
playerv5_tools_mcp-0.1.0.dist-info/METADATA
playerv5_tools_mcp-0.1.0.dist-info/WHEEL
playerv5_tools_mcp-0.1.0.dist-info/entry_points.txt
playerv5_tools_mcp-0.1.0.dist-info/RECORD
