Metadata-Version: 2.4
Name: playerv5-tools-mcp
Version: 0.1.0
Summary: Add your description here
Author-email: player <chenwei_767@qq.com>
Requires-Python: >=3.13
Requires-Dist: mcp[cli]>=1.9.3
